onica_iotloader/__init__.py
onica_iotloader/cli.py
onica_iotloader/loader.py
onica_iotloader-0.1.2.dist-info/LICENSE.txt
onica_iotloader-0.1.2.dist-info/METADATA
onica_iotloader-0.1.2.dist-info/WHEEL
onica_iotloader-0.1.2.dist-info/entry_points.txt
onica_iotloader-0.1.2.dist-info/top_level.txt
onica_iotloader-0.1.2.dist-info/RECORD
