Metadata-Version: 2.1
Name: onica-iotloader
Version: 0.1.2
Summary: A tool to load bulk simulation data into AWS IoT Analytics
Home-page: https://github.com/onicagroup/onica-iotloader
Author: Onica Group LLC
Author-email: opensource@onica.com
License: Apache License 2.0
Keywords: iot cli
Platform: UNKNOWN
Classifier: Development Status :: 3 - Alpha
Classifier: Intended Audience :: Developers
Classifier: Topic :: Utilities
Classifier: Programming Language :: Python :: 2
Classifier: Programming Language :: Python :: 2.7
Requires-Dist: boto3
Requires-Dist: docopt
Provides-Extra: dev
Requires-Dist: check-manifest; extra == 'dev'
Provides-Extra: test
Requires-Dist: coverage; extra == 'test'
